nbserv_client/__init__.py
nbserv_client/api/__init__.py
nbserv_client/api/api_spec_api.py
nbserv_client/api/config_api.py
nbserv_client/api/contents_api.py
nbserv_client/api/default_api.py
nbserv_client/api/identity_api.py
nbserv_client/api/kernels_api.py
nbserv_client/api/kernelspecs_api.py
nbserv_client/api/sessions_api.py
nbserv_client/api/status_api.py
nbserv_client/api/terminals_api.py
nbserv_client/api_client.py
nbserv_client/api_response.py
nbserv_client/configuration.py
nbserv_client/exceptions.py
nbserv_client/models/__init__.py
nbserv_client/models/api_contents_path_get400_response.py
nbserv_client/models/api_contents_path_post_request.py
nbserv_client/models/api_contents_path_put_request.py
nbserv_client/models/api_get200_response.py
nbserv_client/models/api_kernels_post_request.py
nbserv_client/models/api_kernelspecs_get200_response.py
nbserv_client/models/api_me_get200_response.py
nbserv_client/models/api_sessions_post501_response.py
nbserv_client/models/api_status.py
nbserv_client/models/checkpoints.py
nbserv_client/models/contents.py
nbserv_client/models/identity.py
nbserv_client/models/kernel.py
nbserv_client/models/kernel_spec.py
nbserv_client/models/kernel_spec_file.py
nbserv_client/models/kernel_spec_file_help_links_inner.py
nbserv_client/models/kernel_spec_resources.py
nbserv_client/models/session.py
nbserv_client/models/terminal.py
nbserv_client/py.typed
nbserv_client/rest.py
nbserv_client-1.5.0.dist-info/METADATA
nbserv_client-1.5.0.dist-info/WHEEL
nbserv_client-1.5.0.dist-info/RECORD
