Metadata-Version: 2.1
Name: nbserv-client
Version: 1.5.0
Summary: Jupyter Server API
Home-page: https://github.com/americandatascience/nbserv-client
License: BSD-3-Clause
Keywords: OpenAPI,OpenAPI-Generator,Jupyter Server API
Author: Andrew Chang
Requires-Python: >=3.7,<4.0
Classifier: License :: OSI Approved :: BSD License
Classifier: Programming Language :: Python :: 3
Classifier: Programming Language :: Python :: 3.7
Classifier: Programming Language :: Python :: 3.8
Classifier: Programming Language :: Python :: 3.9
Classifier: Programming Language :: Python :: 3.10
Classifier: Programming Language :: Python :: 3.11
Requires-Dist: pydantic (>=2)
Requires-Dist: python-dateutil (>=2.8.2)
Requires-Dist: typing-extensions (>=4.7.1)
Requires-Dist: urllib3 (>=1.25.3)
Project-URL: Repository, https://github.com/americandatascience/nbserv-client
